Compiled from "prog.kt"
public final class ProgKt {
  public static final void main();
    Code:
       0: new           #8                  // class Msg
       3: dup
       4: ldc           #10                 // String Hello, world!
       6: invokespecial #14                 // Method Msg."<init>":(Ljava/lang/String;)V
       9: astore_0
      10: aload_0
      11: invokevirtual #17                 // Method Msg.show:()V
      14: return

  public static void main(java.lang.String[]);
    Code:
       0: invokestatic  #22                 // Method main:()V
       3: return
}
